setup.py
staticsubset/__init__.py
staticsubset/main.py
staticsubset.egg-info/PKG-INFO
staticsubset.egg-info/SOURCES.txt
staticsubset.egg-info/dependency_links.txt
staticsubset.egg-info/entry_points.txt
staticsubset.egg-info/top_level.txt