Metadata-Version: 1.1
Name: staticsubset
Version: 0.0.2
Summary: static subset
Home-page: https://hydra.ecd.space/f/staticsubset/
Author: Eduard Christian Dumitrescu
Author-email: UNKNOWN
License: LGPLv3
Platform: UNKNOWN
Classifier: Programming Language :: Python :: 3 :: Only
